numfile.py
numfile-0.1.0.dist-info/LICENSE
numfile-0.1.0.dist-info/WHEEL
numfile-0.1.0.dist-info/METADATA
numfile-0.1.0.dist-info/RECORD
