Metadata-Version: 2.1
Name: numfile
Version: 0.1.0
Summary: Automatically assign an increasing sequence number to file names.
Home-page: https://github.com/bzaczynski/numfile
License: UNKNOWN
Author: Bartosz Zaczyński
Author-email: bartosz.zaczynski@gmail.com
Requires-Python: >=3.9
Classifier: License :: OSI Approved :: MIT License
Classifier: Programming Language :: Python :: 3
Requires-Dist: black==20.8b1 ; extra == "dev"
Requires-Dist: bpython==0.20.1 ; extra == "dev"
Requires-Dist: bump2version==1.0.1 ; extra == "dev"
Requires-Dist: flake8==3.8.4 ; extra == "dev"
Requires-Dist: pylint==2.6.0 ; extra == "dev"
Requires-Dist: pytest-mock==3.3.1 ; extra == "dev"
Requires-Dist: pytest==6.1.2 ; extra == "dev"
Provides-Extra: dev
